python_glossary/__init__.py
python_glossary/glossary.py
python_glossary-0.0.2.dist-info/LICENSE
python_glossary-0.0.2.dist-info/METADATA
python_glossary-0.0.2.dist-info/WHEEL
python_glossary-0.0.2.dist-info/top_level.txt
python_glossary-0.0.2.dist-info/RECORD
