Metadata-Version: 2.1
Name: python-glossary
Version: 0.0.2
Summary: Python module that uses free dictionary API to retrieve definitions, examples, synonyms, antonyms, and audio of english words 
Home-page: https://github.com/ilya-smut/python-glossary
Author: Ilya Smut
Author-email: ilya.smut.off.g@gmail.com
License: GPL-3.0 license
Project-URL: Source Code, https://github.com/ilya-smut/python-glossary
Classifier: Intended Audience :: Developers
Classifier: Programming Language :: Python :: 3.12
Requires-Python: >=3.8
License-File: LICENSE
Requires-Dist: requests
